[{
  "id": 10001,
  "name": "グランドセイバー",
  "nameShort": "セイバー",
  "nameShortEnglish": "Saber",
  "classBoardBaseId": 10001,
  "condSvtLv": 100,
  "condSkillLv": 10,
  "condType": "commonRelease",
  "condTargetId": 20145401,
  "condNum": 0,
  "removeItems": [{
    "itemId": 70,
    "amount": 1
  }],
  "details": [{
    "grandGraphId": 10001,
    "baseClassId": 1,
    "grandClassId": 10001,
    "baseClass": "saber",
    "grandClass": "grandSaber",
    "adjustHp": 1000,
    "adjustAtk": 1000,
    "condType": "commonRelease",
    "condTargetId": 20145401,
    "condNum": 0,
    "adjustIndividuality": [{
      "id": 180
    }]
  }]
}, {
  "id": 10003,
  "name": "グランドランサー",
  "nameShort": "ランサー",
  "nameShortEnglish": "Lancer",
  "classBoardBaseId": 10003,
  "condSvtLv": 100,
  "condSkillLv": 10,
  "condType": "commonRelease",
  "condTargetId": 20146801,
  "condNum": 0,
  "removeItems": [{
    "itemId": 70,
    "amount": 1
  }],
  "details": [{
    "grandGraphId": 10003,
    "baseClassId": 3,
    "grandClassId": 10003,
    "baseClass": "lancer",
    "grandClass": "grandLancer",
    "adjustHp": 1000,
    "adjustAtk": 1000,
    "condType": "commonRelease",
    "condTargetId": 20146801,
    "condNum": 0,
    "adjustIndividuality": [{
      "id": 181
    }]
  }]
}, {
  "id": 10007,
  "name": "グランドバーサーカー",
  "nameShort": "バーサーカー",
  "nameShortEnglish": "Berserker",
  "classBoardBaseId": 10007,
  "condSvtLv": 100,
  "condSkillLv": 10,
  "condType": "commonRelease",
  "condTargetId": 20146501,
  "condNum": 0,
  "removeItems": [{
    "itemId": 70,
    "amount": 1
  }],
  "details": [{
    "grandGraphId": 10007,
    "baseClassId": 7,
    "grandClassId": 10007,
    "baseClass": "berserker",
    "grandClass": "grandBerserker",
    "adjustHp": 1000,
    "adjustAtk": 1000,
    "condType": "commonRelease",
    "condTargetId": 20146501,
    "condNum": 0,
    "adjustIndividuality": [{
      "id": 186
    }]
  }]
}, {
  "id": 10008,
  "name": "グランドエクストラ",
  "nameShort": "エクストラ",
  "nameShortEnglish": "Extra",
  "classBoardBaseId": 10008,
  "condSvtLv": 100,
  "condSkillLv": 10,
  "condType": "commonRelease",
  "condTargetId": 20148901,
  "condNum": 0,
  "removeItems": [{
    "itemId": 70,
    "amount": 1
  }],
  "details": [{
    "grandGraphId": 10008,
    "baseClassId": 8,
    "grandClassId": 10008,
    "baseClass": "shielder",
    "grandClass": "10008",
    "adjustHp": 1000,
    "adjustAtk": 1000,
    "condType": "commonRelease",
    "condTargetId": 20148901,
    "condNum": 0,
    "adjustIndividuality": [{
      "id": 187
    }]
  }, {
    "grandGraphId": 10008,
    "baseClassId": 9,
    "grandClassId": 10009,
    "baseClass": "ruler",
    "grandClass": "10009",
    "adjustHp": 1000,
    "adjustAtk": 1000,
    "condType": "commonRelease",
    "condTargetId": 20148901,
    "condNum": 0,
    "adjustIndividuality": [{
      "id": 188
    }]
  }, {
    "grandGraphId": 10008,
    "baseClassId": 10,
    "grandClassId": 10010,
    "baseClass": "alterEgo",
    "grandClass": "10010",
    "adjustHp": 1000,
    "adjustAtk": 1000,
    "condType": "commonRelease",
    "condTargetId": 20148901,
    "condNum": 0,
    "adjustIndividuality": [{
      "id": 189
    }]
  }, {
    "grandGraphId": 10008,
    "baseClassId": 11,
    "grandClassId": 10011,
    "baseClass": "avenger",
    "grandClass": "10011",
    "adjustHp": 1000,
    "adjustAtk": 1000,
    "condType": "commonRelease",
    "condTargetId": 20148901,
    "condNum": 0,
    "adjustIndividuality": [{
      "id": 190
    }]
  }, {
    "grandGraphId": 10008,
    "baseClassId": 23,
    "grandClassId": 10023,
    "baseClass": "moonCancer",
    "grandClass": "10023",
    "adjustHp": 1000,
    "adjustAtk": 1000,
    "condType": "commonRelease",
    "condTargetId": 20148901,
    "condNum": 0,
    "adjustIndividuality": [{
      "id": 191
    }]
  }, {
    "grandGraphId": 10008,
    "baseClassId": 25,
    "grandClassId": 10025,
    "baseClass": "foreigner",
    "grandClass": "10025",
    "adjustHp": 1000,
    "adjustAtk": 1000,
    "condType": "commonRelease",
    "condTargetId": 20148901,
    "condNum": 0,
    "adjustIndividuality": [{
      "id": 192
    }]
  }, {
    "grandGraphId": 10008,
    "baseClassId": 28,
    "grandClassId": 10028,
    "baseClass": "pretender",
    "grandClass": "10028",
    "adjustHp": 1000,
    "adjustAtk": 1000,
    "condType": "commonRelease",
    "condTargetId": 20148901,
    "condNum": 0,
    "adjustIndividuality": [{
      "id": 193
    }]
  }, {
    "grandGraphId": 10008,
    "baseClassId": 33,
    "grandClassId": 10033,
    "baseClass": "beast",
    "grandClass": "10033",
    "adjustHp": 1000,
    "adjustAtk": 1000,
    "condType": "commonRelease",
    "condTargetId": 20148902,
    "condNum": 0,
    "adjustIndividuality": [{
      "id": 194
    }]
  }, {
    "grandGraphId": 10008,
    "baseClassId": 38,
    "grandClassId": 10038,
    "baseClass": "beastEresh",
    "grandClass": "10038",
    "adjustHp": 1000,
    "adjustAtk": 1000,
    "condType": "commonRelease",
    "condTargetId": 20148902,
    "condNum": 0,
    "adjustIndividuality": [{
      "id": 194
    }]
  }, {
    "grandGraphId": 10008,
    "baseClassId": 40,
    "grandClassId": 10040,
    "baseClass": "unBeast",
    "grandClass": "10040",
    "adjustHp": 1000,
    "adjustAtk": 1000,
    "condType": "commonRelease",
    "condTargetId": 20148902,
    "condNum": 0,
    "adjustIndividuality": [{
      "id": 194
    }]
  }]
}, {
  "id": 10009,
  "name": "グランドエクストラ",
  "nameShort": "エクストラ",
  "nameShortEnglish": "Extra",
  "classBoardBaseId": 10009,
  "condSvtLv": 100,
  "condSkillLv": 10,
  "condType": "commonRelease",
  "condTargetId": 20148901,
  "condNum": 0,
  "removeItems": [{
    "itemId": 70,
    "amount": 1
  }],
  "details": [{
    "grandGraphId": 10009,
    "baseClassId": 8,
    "grandClassId": 10008,
    "baseClass": "shielder",
    "grandClass": "10008",
    "adjustHp": 1000,
    "adjustAtk": 1000,
    "condType": "commonRelease",
    "condTargetId": 20148901,
    "condNum": 0,
    "adjustIndividuality": [{
      "id": 187
    }]
  }, {
    "grandGraphId": 10009,
    "baseClassId": 9,
    "grandClassId": 10009,
    "baseClass": "ruler",
    "grandClass": "10009",
    "adjustHp": 1000,
    "adjustAtk": 1000,
    "condType": "commonRelease",
    "condTargetId": 20148901,
    "condNum": 0,
    "adjustIndividuality": [{
      "id": 188
    }]
  }, {
    "grandGraphId": 10009,
    "baseClassId": 10,
    "grandClassId": 10010,
    "baseClass": "alterEgo",
    "grandClass": "10010",
    "adjustHp": 1000,
    "adjustAtk": 1000,
    "condType": "commonRelease",
    "condTargetId": 20148901,
    "condNum": 0,
    "adjustIndividuality": [{
      "id": 189
    }]
  }, {
    "grandGraphId": 10009,
    "baseClassId": 11,
    "grandClassId": 10011,
    "baseClass": "avenger",
    "grandClass": "10011",
    "adjustHp": 1000,
    "adjustAtk": 1000,
    "condType": "commonRelease",
    "condTargetId": 20148901,
    "condNum": 0,
    "adjustIndividuality": [{
      "id": 190
    }]
  }, {
    "grandGraphId": 10009,
    "baseClassId": 23,
    "grandClassId": 10023,
    "baseClass": "moonCancer",
    "grandClass": "10023",
    "adjustHp": 1000,
    "adjustAtk": 1000,
    "condType": "commonRelease",
    "condTargetId": 20148901,
    "condNum": 0,
    "adjustIndividuality": [{
      "id": 191
    }]
  }, {
    "grandGraphId": 10009,
    "baseClassId": 25,
    "grandClassId": 10025,
    "baseClass": "foreigner",
    "grandClass": "10025",
    "adjustHp": 1000,
    "adjustAtk": 1000,
    "condType": "commonRelease",
    "condTargetId": 20148901,
    "condNum": 0,
    "adjustIndividuality": [{
      "id": 192
    }]
  }, {
    "grandGraphId": 10009,
    "baseClassId": 28,
    "grandClassId": 10028,
    "baseClass": "pretender",
    "grandClass": "10028",
    "adjustHp": 1000,
    "adjustAtk": 1000,
    "condType": "commonRelease",
    "condTargetId": 20148901,
    "condNum": 0,
    "adjustIndividuality": [{
      "id": 193
    }]
  }, {
    "grandGraphId": 10009,
    "baseClassId": 33,
    "grandClassId": 10033,
    "baseClass": "beast",
    "grandClass": "10033",
    "adjustHp": 1000,
    "adjustAtk": 1000,
    "condType": "commonRelease",
    "condTargetId": 20148902,
    "condNum": 0,
    "adjustIndividuality": [{
      "id": 194
    }]
  }, {
    "grandGraphId": 10009,
    "baseClassId": 38,
    "grandClassId": 10038,
    "baseClass": "beastEresh",
    "grandClass": "10038",
    "adjustHp": 1000,
    "adjustAtk": 1000,
    "condType": "commonRelease",
    "condTargetId": 20148902,
    "condNum": 0,
    "adjustIndividuality": [{
      "id": 194
    }]
  }, {
    "grandGraphId": 10009,
    "baseClassId": 40,
    "grandClassId": 10040,
    "baseClass": "unBeast",
    "grandClass": "10040",
    "adjustHp": 1000,
    "adjustAtk": 1000,
    "condType": "commonRelease",
    "condTargetId": 20148902,
    "condNum": 0,
    "adjustIndividuality": [{
      "id": 194
    }]
  }]
}]
