{
  "timestamp": 1758546389,
  "utc": "2025-09-22T13:06:29",
  "minimalApp": "2.5.21",
  "files": {
    "items.json": {
      "key": "items",
      "filename": "items.json",
      "size": 958072,
      "hash": "45f390",
      "minSize": 839390,
      "minHash": "14d5a7",
      "timestamp": 1758531966
    },
    "entities.json": {
      "key": "entities",
      "filename": "entities.json",
      "size": 1804858,
      "hash": "74b35d",
      "minSize": 1363718,
      "minHash": "37864a",
      "timestamp": 1758531966
    },
    "bgms.json": {
      "key": "bgms",
      "filename": "bgms.json",
      "size": 544810,
      "hash": "252aea",
      "minSize": 448932,
      "minHash": "b2117c",
      "timestamp": 1757235961
    },
    "servants.1.json": {
      "key": "servants",
      "filename": "servants.1.json",
      "size": 1900876,
      "hash": "88352f",
      "minSize": 1256987,
      "minHash": "0d3166",
      "timestamp": 1757070378
    },
    "servants.2.json": {
      "key": "servants",
      "filename": "servants.2.json",
      "size": 1813338,
      "hash": "b8470b",
      "minSize": 1196560,
      "minHash": "5c263c",
      "timestamp": 1757070378
    },
    "servants.3.json": {
      "key": "servants",
      "filename": "servants.3.json",
      "size": 1903047,
      "hash": "639d89",
      "minSize": 1254542,
      "minHash": "21ac2d",
      "timestamp": 1757070378
    },
    "servants.4.json": {
      "key": "servants",
      "filename": "servants.4.json",
      "size": 1725413,
      "hash": "ba3209",
      "minSize": 1142019,
      "minHash": "aaf3e6",
      "timestamp": 1757070378
    },
    "servants.5.json": {
      "key": "servants",
      "filename": "servants.5.json",
      "size": 800158,
      "hash": "3c715e",
      "minSize": 515859,
      "minHash": "18838f",
      "timestamp": 1757709743
    },
    "craftEssences.1.json": {
      "key": "craftEssences",
      "filename": "craftEssences.1.json",
      "size": 574426,
      "hash": "af8ace",
      "minSize": 411423,
      "minHash": "926b31",
      "timestamp": 1709727925
    },
    "craftEssences.2.json": {
      "key": "craftEssences",
      "filename": "craftEssences.2.json",
      "size": 598848,
      "hash": "6e795c",
      "minSize": 430876,
      "minHash": "e530e0",
      "timestamp": 1709727925
    },
    "craftEssences.3.json": {
      "key": "craftEssences",
      "filename": "craftEssences.3.json",
      "size": 608347,
      "hash": "d97d00",
      "minSize": 435823,
      "minHash": "3b9d89",
      "timestamp": 1743585600
    },
    "craftEssences.4.json": {
      "key": "craftEssences",
      "filename": "craftEssences.4.json",
      "size": 621147,
      "hash": "feacb9",
      "minSize": 445254,
      "minHash": "2de14b",
      "timestamp": 1717856996
    },
    "craftEssences.5.json": {
      "key": "craftEssences",
      "filename": "craftEssences.5.json",
      "size": 582899,
      "hash": "154e6a",
      "minSize": 421753,
      "minHash": "316229",
      "timestamp": 1758531966
    },
    "commandCodes.json": {
      "key": "commandCodes",
      "filename": "commandCodes.json",
      "size": 167741,
      "hash": "956da8",
      "minSize": 142853,
      "minHash": "e6ae8c",
      "timestamp": 1755084205
    },
    "mysticCodes.json": {
      "key": "mysticCodes",
      "filename": "mysticCodes.json",
      "size": 42537,
      "hash": "db01dc",
      "minSize": 34497,
      "minHash": "ceab95",
      "timestamp": 1735659863
    },
    "exchangeTickets.json": {
      "key": "exchangeTickets",
      "filename": "exchangeTickets.json",
      "size": 11836,
      "hash": "d1e904",
      "minSize": 9024,
      "minHash": "5cc546",
      "timestamp": 1756652743
    },
    "enemyMasters.json": {
      "key": "enemyMasters",
      "filename": "enemyMasters.json",
      "size": 20010,
      "hash": "dfbcce",
      "minSize": 17476,
      "minHash": "9010d7",
      "timestamp": 1746024601
    },
    "classBoards.json": {
      "key": "classBoards",
      "filename": "classBoards.json",
      "size": 457328,
      "hash": "f8ef24",
      "minSize": 295073,
      "minHash": "58429a",
      "timestamp": 1757408741
    },
    "grandGraphs.json": {
      "key": "grandGraphs",
      "filename": "grandGraphs.json",
      "size": 11996,
      "hash": "85a929",
      "minSize": 9332,
      "minHash": "b814cd",
      "timestamp": 1757408741
    },
    "masterMissions.json": {
      "key": "masterMissions",
      "filename": "masterMissions.json",
      "size": 76586,
      "hash": "35fdd0",
      "minSize": 60557,
      "minHash": "0f57d5",
      "timestamp": 1758531966
    },
    "mappingData.1.json": {
      "key": "mappingData",
      "filename": "mappingData.1.json",
      "size": 3683294,
      "hash": "c4db02",
      "minSize": 3454897,
      "minHash": "ffc75c",
      "timestamp": 1742637213
    },
    "mappingData.2.json": {
      "key": "mappingData",
      "filename": "mappingData.2.json",
      "size": 1888319,
      "hash": "0ce5a0",
      "minSize": 1556039,
      "minHash": "05da63",
      "timestamp": 1742637213
    },
    "mappingData.3.json": {
      "key": "mappingData",
      "filename": "mappingData.3.json",
      "size": 3345841,
      "hash": "00d45d",
      "minSize": 2537979,
      "minHash": "6c0245",
      "timestamp": 1742637213
    },
    "mappingPatch.json": {
      "key": "mappingPatch",
      "filename": "mappingPatch.json",
      "size": 1404387,
      "hash": "a8bd1b",
      "minSize": 1222088,
      "minHash": "85bd6b",
      "timestamp": 1758546389
    },
    "events.1.json": {
      "key": "events",
      "filename": "events.1.json",
      "size": 2791576,
      "hash": "e83f24",
      "minSize": 1946900,
      "minHash": "c94a8b",
      "timestamp": 1718184473
    },
    "events.2.json": {
      "key": "events",
      "filename": "events.2.json",
      "size": 3965358,
      "hash": "642b12",
      "minSize": 2867771,
      "minHash": "e6872e",
      "timestamp": 1720847859
    },
    "events.3.json": {
      "key": "events",
      "filename": "events.3.json",
      "size": 3815276,
      "hash": "9f9f2e",
      "minSize": 2719374,
      "minHash": "da8942",
      "timestamp": 1743585600
    },
    "events.4.json": {
      "key": "events",
      "filename": "events.4.json",
      "size": 5653380,
      "hash": "8015c4",
      "minSize": 4131915,
      "minHash": "db8557",
      "timestamp": 1758531966
    },
    "events.5.json": {
      "key": "events",
      "filename": "events.5.json",
      "size": 2189913,
      "hash": "8bfe74",
      "minSize": 1542949,
      "minHash": "0b77fa",
      "timestamp": 1758186457
    },
    "wars.1.json": {
      "key": "wars",
      "filename": "wars.1.json",
      "size": 4166603,
      "hash": "5b995a",
      "minSize": 2919075,
      "minHash": "174a93",
      "timestamp": 1758186457
    },
    "wars.2.json": {
      "key": "wars",
      "filename": "wars.2.json",
      "size": 2621646,
      "hash": "48bc2f",
      "minSize": 1783645,
      "minHash": "b0ef3c",
      "timestamp": 1758186457
    },
    "wars.3.json": {
      "key": "wars",
      "filename": "wars.3.json",
      "size": 2834307,
      "hash": "83c2f4",
      "minSize": 1952071,
      "minHash": "50c8bf",
      "timestamp": 1718184473
    },
    "wars.4.json": {
      "key": "wars",
      "filename": "wars.4.json",
      "size": 3835430,
      "hash": "f60da9",
      "minSize": 2679376,
      "minHash": "af0a60",
      "timestamp": 1718184473
    },
    "wars.5.json": {
      "key": "wars",
      "filename": "wars.5.json",
      "size": 4783756,
      "hash": "5df4fc",
      "minSize": 3397246,
      "minHash": "edc883",
      "timestamp": 1756890342
    },
    "dropData.json": {
      "key": "dropData",
      "filename": "dropData.json",
      "size": 1285898,
      "hash": "ba724c",
      "minSize": 678411,
      "minHash": "811e25",
      "timestamp": 1758546389
    },
    "questPhases.1.json": {
      "key": "questPhases",
      "filename": "questPhases.1.json",
      "size": 1016578,
      "hash": "be8d52",
      "minSize": 579816,
      "minHash": "f294cc",
      "timestamp": 1756458333
    },
    "questPhases.2.json": {
      "key": "questPhases",
      "filename": "questPhases.2.json",
      "size": 1111362,
      "hash": "eba6aa",
      "minSize": 627770,
      "minHash": "85a273",
      "timestamp": 1756458333
    },
    "questPhases.3.json": {
      "key": "questPhases",
      "filename": "questPhases.3.json",
      "size": 1107961,
      "hash": "2a1b00",
      "minSize": 632667,
      "minHash": "44c2dc",
      "timestamp": 1755177850
    },
    "questPhases.4.json": {
      "key": "questPhases",
      "filename": "questPhases.4.json",
      "size": 303289,
      "hash": "2bb3bc",
      "minSize": 173280,
      "minHash": "10c5c3",
      "timestamp": 1756998321
    },
    "extraMasterMission.json": {
      "key": "extraMasterMission",
      "filename": "extraMasterMission.json",
      "size": 2287026,
      "hash": "509559",
      "minSize": 1824721,
      "minHash": "bc51af",
      "timestamp": 1758531966
    },
    "questGroups.json": {
      "key": "questGroups",
      "filename": "questGroups.json",
      "size": 1089272,
      "hash": "c712ea",
      "minSize": 834556,
      "minHash": "c8782c",
      "timestamp": 1758099938
    },
    "questPhaseDetails.1.json": {
      "key": "questPhaseDetails",
      "filename": "questPhaseDetails.1.json",
      "size": 122120,
      "hash": "5994bb",
      "minSize": 92199,
      "minHash": "77ac77",
      "timestamp": 1733911505
    },
    "questPhaseDetails.2.json": {
      "key": "questPhaseDetails",
      "filename": "questPhaseDetails.2.json",
      "size": 470516,
      "hash": "f23f7f",
      "minSize": 354779,
      "minHash": "ce5cdf",
      "timestamp": 1743240019
    },
    "questPhaseDetails.3.json": {
      "key": "questPhaseDetails",
      "filename": "questPhaseDetails.3.json",
      "size": 755182,
      "hash": "724c82",
      "minSize": 569048,
      "minHash": "a33820",
      "timestamp": 1743240019
    },
    "questPhaseDetails.4.json": {
      "key": "questPhaseDetails",
      "filename": "questPhaseDetails.4.json",
      "size": 322430,
      "hash": "835753",
      "minSize": 243776,
      "minHash": "45e9ae",
      "timestamp": 1757995550
    },
    "mstGacha.1.json": {
      "key": "mstGacha",
      "filename": "mstGacha.1.json",
      "size": 518276,
      "hash": "8c82d3",
      "minSize": 457836,
      "minHash": "715c27",
      "timestamp": 1702498907
    },
    "mstGacha.2.json": {
      "key": "mstGacha",
      "filename": "mstGacha.2.json",
      "size": 242667,
      "hash": "b95fde",
      "minSize": 213107,
      "minHash": "6d14fd",
      "timestamp": 1758531966
    },
    "campaigns.json": {
      "key": "campaigns",
      "filename": "campaigns.json",
      "size": 67572,
      "hash": "28561e",
      "minSize": 59542,
      "minHash": "7e471d",
      "timestamp": 1758546389
    },
    "constData.json": {
      "key": "constData",
      "filename": "constData.json",
      "size": 235895,
      "hash": "6c8f75",
      "minSize": 167606,
      "minHash": "36faf9",
      "timestamp": 1757775940
    },
    "wiki.servants.1.json": {
      "key": "wiki.servants",
      "filename": "wiki.servants.1.json",
      "size": 142804,
      "hash": "cd148d",
      "minSize": 135691,
      "minHash": "100ea7",
      "timestamp": 1755267667
    },
    "wiki.servants.2.json": {
      "key": "wiki.servants",
      "filename": "wiki.servants.2.json",
      "size": 126819,
      "hash": "04c211",
      "minSize": 120100,
      "minHash": "841283",
      "timestamp": 1739412589
    },
    "wiki.servants.3.json": {
      "key": "wiki.servants",
      "filename": "wiki.servants.3.json",
      "size": 131023,
      "hash": "0c6c5d",
      "minSize": 124161,
      "minHash": "c82a93",
      "timestamp": 1755173501
    },
    "wiki.servants.4.json": {
      "key": "wiki.servants",
      "filename": "wiki.servants.4.json",
      "size": 86129,
      "hash": "0f7fa5",
      "minSize": 81007,
      "minHash": "c933f2",
      "timestamp": 1756299934
    },
    "wiki.servants.5.json": {
      "key": "wiki.servants",
      "filename": "wiki.servants.5.json",
      "size": 169769,
      "hash": "4ebbe4",
      "minSize": 166698,
      "minHash": "a15be6",
      "timestamp": 1758287050
    },
    "wiki.craftEssences.1.json": {
      "key": "wiki.craftEssences",
      "filename": "wiki.craftEssences.1.json",
      "size": 1042021,
      "hash": "6b3d9c",
      "minSize": 1013266,
      "minHash": "08d6f0",
      "timestamp": 1755173501
    },
    "wiki.craftEssences.2.json": {
      "key": "wiki.craftEssences",
      "filename": "wiki.craftEssences.2.json",
      "size": 1107791,
      "hash": "5c5820",
      "minSize": 1078286,
      "minHash": "9baba3",
      "timestamp": 1755173501
    },
    "wiki.craftEssences.3.json": {
      "key": "wiki.craftEssences",
      "filename": "wiki.craftEssences.3.json",
      "size": 1218928,
      "hash": "9017b8",
      "minSize": 1189217,
      "minHash": "02bb06",
      "timestamp": 1755173501
    },
    "wiki.craftEssences.4.json": {
      "key": "wiki.craftEssences",
      "filename": "wiki.craftEssences.4.json",
      "size": 1214775,
      "hash": "419387",
      "minSize": 1186069,
      "minHash": "8387ea",
      "timestamp": 1758035135
    },
    "wiki.craftEssences.5.json": {
      "key": "wiki.craftEssences",
      "filename": "wiki.craftEssences.5.json",
      "size": 438465,
      "hash": "6fa8ae",
      "minSize": 420958,
      "minHash": "3ba0a9",
      "timestamp": 1758546389
    },
    "wiki.commandCodes.json": {
      "key": "wiki.commandCodes",
      "filename": "wiki.commandCodes.json",
      "size": 285330,
      "hash": "775820",
      "minSize": 275566,
      "minHash": "8ccff4",
      "timestamp": 1758035135
    },
    "wiki.events.1.json": {
      "key": "wiki.events",
      "filename": "wiki.events.1.json",
      "size": 545295,
      "hash": "820566",
      "minSize": 431074,
      "minHash": "0ff95c",
      "timestamp": 1758531966
    },
    "wiki.events.2.json": {
      "key": "wiki.events",
      "filename": "wiki.events.2.json",
      "size": 240023,
      "hash": "4f4698",
      "minSize": 208727,
      "minHash": "9833ba",
      "timestamp": 1758546389
    },
    "wiki.wars.json": {
      "key": "wiki.wars",
      "filename": "wiki.wars.json",
      "size": 22150,
      "hash": "d410d8",
      "minSize": 19535,
      "minHash": "ce39f2",
      "timestamp": 1757425255
    },
    "wiki.summons.1.json": {
      "key": "wiki.summons",
      "filename": "wiki.summons.1.json",
      "size": 222762,
      "hash": "7ac671",
      "minSize": 163642,
      "minHash": "6818fa",
      "timestamp": 1735563501
    },
    "wiki.summons.2.json": {
      "key": "wiki.summons",
      "filename": "wiki.summons.2.json",
      "size": 809965,
      "hash": "35931a",
      "minSize": 556644,
      "minHash": "171dbb",
      "timestamp": 1735563501
    },
    "wiki.summons.3.json": {
      "key": "wiki.summons",
      "filename": "wiki.summons.3.json",
      "size": 906246,
      "hash": "6263f9",
      "minSize": 630435,
      "minHash": "c8144e",
      "timestamp": 1735563501
    },
    "wiki.summons.4.json": {
      "key": "wiki.summons",
      "filename": "wiki.summons.4.json",
      "size": 766457,
      "hash": "df9132",
      "minSize": 541608,
      "minHash": "024c55",
      "timestamp": 1735407472
    },
    "wiki.summons.5.json": {
      "key": "wiki.summons",
      "filename": "wiki.summons.5.json",
      "size": 647408,
      "hash": "80a0a8",
      "minSize": 465424,
      "minHash": "f7f8cf",
      "timestamp": 1754053867
    },
    "wiki.summons.6.json": {
      "key": "wiki.summons",
      "filename": "wiki.summons.6.json",
      "size": 233964,
      "hash": "a76676",
      "minSize": 176459,
      "minHash": "8403c2",
      "timestamp": 1758546389
    },
    "wiki.webcrowMapping.json": {
      "key": "wiki.webcrowMapping",
      "filename": "wiki.webcrowMapping.json",
      "size": 5303,
      "hash": "6a4414",
      "minSize": 5303,
      "minHash": "6a4414",
      "timestamp": 1703495738
    },
    "baseTds.json": {
      "key": "baseTds",
      "filename": "baseTds.json",
      "size": 2492821,
      "hash": "e8cdd4",
      "minSize": 1651631,
      "minHash": "6ce3f1",
      "timestamp": 1757070378
    },
    "baseSkills.json": {
      "key": "baseSkills",
      "filename": "baseSkills.json",
      "size": 6493084,
      "hash": "80d746",
      "minSize": 4751945,
      "minHash": "8e08e7",
      "timestamp": 1758531966
    },
    "baseFunctions.json": {
      "key": "baseFunctions",
      "filename": "baseFunctions.json",
      "size": 1739527,
      "hash": "eb9d0d",
      "minSize": 1378458,
      "minHash": "848987",
      "timestamp": 1757709743
    }
  }
}
