{
  "timestamp": 1691723153,
  "utc": "2023-08-11T03:05:53",
  "minimalApp": "2.4.6",
  "files": {
    "items.json": {
      "key": "items",
      "filename": "items.json",
      "size": 685161,
      "hash": "cc0127",
      "minSize": 608779,
      "minHash": "d54e61",
      "timestamp": 1691554882
    },
    "entities.json": {
      "key": "entities",
      "filename": "entities.json",
      "size": 948906,
      "hash": "4b989b",
      "minSize": 774721,
      "minHash": "fc9e29",
      "timestamp": 1691554882
    },
    "bgms.json": {
      "key": "bgms",
      "filename": "bgms.json",
      "size": 408399,
      "hash": "6ba62c",
      "minSize": 334588,
      "minHash": "218632",
      "timestamp": 1690709824
    },
    "servants.1.json": {
      "key": "servants",
      "filename": "servants.1.json",
      "size": 1441578,
      "hash": "72e23d",
      "minSize": 952015,
      "minHash": "f7df85",
      "timestamp": 1691054148
    },
    "servants.2.json": {
      "key": "servants",
      "filename": "servants.2.json",
      "size": 1364401,
      "hash": "9ca98b",
      "minSize": 901309,
      "minHash": "29a6ac",
      "timestamp": 1691313402
    },
    "servants.3.json": {
      "key": "servants",
      "filename": "servants.3.json",
      "size": 1440543,
      "hash": "e0182e",
      "minSize": 948223,
      "minHash": "08260e",
      "timestamp": 1691226992
    },
    "servants.4.json": {
      "key": "servants",
      "filename": "servants.4.json",
      "size": 1076182,
      "hash": "0124c7",
      "minSize": 710192,
      "minHash": "362e72",
      "timestamp": 1690779850
    },
    "craftEssences.1.json": {
      "key": "craftEssences",
      "filename": "craftEssences.1.json",
      "size": 556373,
      "hash": "cc2c30",
      "minSize": 395594,
      "minHash": "df26ca",
      "timestamp": 1687653084
    },
    "craftEssences.2.json": {
      "key": "craftEssences",
      "filename": "craftEssences.2.json",
      "size": 575539,
      "hash": "1f739c",
      "minSize": 410495,
      "minHash": "dea62f",
      "timestamp": 1687653084
    },
    "craftEssences.3.json": {
      "key": "craftEssences",
      "filename": "craftEssences.3.json",
      "size": 580726,
      "hash": "fd09bf",
      "minSize": 412234,
      "minHash": "e1ccad",
      "timestamp": 1687653084
    },
    "craftEssences.4.json": {
      "key": "craftEssences",
      "filename": "craftEssences.4.json",
      "size": 461475,
      "hash": "ff3cc4",
      "minSize": 327979,
      "minHash": "02364e",
      "timestamp": 1691554882
    },
    "commandCodes.json": {
      "key": "commandCodes",
      "filename": "commandCodes.json",
      "size": 115934,
      "hash": "2eb084",
      "minSize": 98122,
      "minHash": "1ed6d9",
      "timestamp": 1690709824
    },
    "mysticCodes.json": {
      "key": "mysticCodes",
      "filename": "mysticCodes.json",
      "size": 35124,
      "hash": "88749c",
      "minSize": 28344,
      "minHash": "033baf",
      "timestamp": 1687101619
    },
    "exchangeTickets.json": {
      "key": "exchangeTickets",
      "filename": "exchangeTickets.json",
      "size": 6673,
      "hash": "f7c912",
      "minSize": 5032,
      "minHash": "d28928",
      "timestamp": 1690816524
    },
    "enemyMasters.json": {
      "key": "enemyMasters",
      "filename": "enemyMasters.json",
      "size": 13392,
      "hash": "491ab3",
      "minSize": 11733,
      "minHash": "3ab51c",
      "timestamp": 1687101619
    },
    "classBoards.json": {
      "key": "classBoards",
      "filename": "classBoards.json",
      "size": 370678,
      "hash": "cbd278",
      "minSize": 236790,
      "minHash": "ad59af",
      "timestamp": 1691014956
    },
    "mappingData.1.json": {
      "key": "mappingData",
      "filename": "mappingData.1.json",
      "size": 2888139,
      "hash": "3a3577",
      "minSize": 2701571,
      "minHash": "a4275b",
      "timestamp": 1688030004
    },
    "mappingData.2.json": {
      "key": "mappingData",
      "filename": "mappingData.2.json",
      "size": 1537010,
      "hash": "6b1373",
      "minSize": 1261451,
      "minHash": "7387f7",
      "timestamp": 1688028348
    },
    "mappingData.3.json": {
      "key": "mappingData",
      "filename": "mappingData.3.json",
      "size": 2586088,
      "hash": "d507d5",
      "minSize": 1933936,
      "minHash": "a3934e",
      "timestamp": 1688028348
    },
    "mappingPatch.json": {
      "key": "mappingPatch",
      "filename": "mappingPatch.json",
      "size": 704817,
      "hash": "61e5eb",
      "minSize": 617145,
      "minHash": "c822c2",
      "timestamp": 1691671450
    },
    "events.1.json": {
      "key": "events",
      "filename": "events.1.json",
      "size": 2579379,
      "hash": "e8e6ee",
      "minSize": 1798046,
      "minHash": "7c39f2",
      "timestamp": 1690741915
    },
    "events.2.json": {
      "key": "events",
      "filename": "events.2.json",
      "size": 3657240,
      "hash": "a184e4",
      "minSize": 2637344,
      "minHash": "d3301b",
      "timestamp": 1690816524
    },
    "events.3.json": {
      "key": "events",
      "filename": "events.3.json",
      "size": 3507285,
      "hash": "0b8774",
      "minSize": 2515428,
      "minHash": "1f2fd6",
      "timestamp": 1690741915
    },
    "events.4.json": {
      "key": "events",
      "filename": "events.4.json",
      "size": 1525577,
      "hash": "de6fed",
      "minSize": 1081572,
      "minHash": "857440",
      "timestamp": 1691554882
    },
    "events.5.json": {
      "key": "events",
      "filename": "events.5.json",
      "size": 1314751,
      "hash": "5ff794",
      "minSize": 926455,
      "minHash": "f5af05",
      "timestamp": 1691554882
    },
    "wars.1.json": {
      "key": "wars",
      "filename": "wars.1.json",
      "size": 3187162,
      "hash": "7908b7",
      "minSize": 2228226,
      "minHash": "f9f898",
      "timestamp": 1691554882
    },
    "wars.2.json": {
      "key": "wars",
      "filename": "wars.2.json",
      "size": 2050885,
      "hash": "862de6",
      "minSize": 1402331,
      "minHash": "0f4081",
      "timestamp": 1688721268
    },
    "wars.3.json": {
      "key": "wars",
      "filename": "wars.3.json",
      "size": 2794143,
      "hash": "790d29",
      "minSize": 1929301,
      "minHash": "abd940",
      "timestamp": 1687653084
    },
    "wars.4.json": {
      "key": "wars",
      "filename": "wars.4.json",
      "size": 3777200,
      "hash": "663995",
      "minSize": 2643982,
      "minHash": "323163",
      "timestamp": 1687653084
    },
    "wars.5.json": {
      "key": "wars",
      "filename": "wars.5.json",
      "size": 2747533,
      "hash": "7a0526",
      "minSize": 1945367,
      "minHash": "a0a3bf",
      "timestamp": 1688894076
    },
    "dropData.json": {
      "key": "dropData",
      "filename": "dropData.json",
      "size": 888824,
      "hash": "76d12b",
      "minSize": 469347,
      "minHash": "093364",
      "timestamp": 1691723153
    },
    "questPhases.1.json": {
      "key": "questPhases",
      "filename": "questPhases.1.json",
      "size": 991905,
      "hash": "5acfa3",
      "minSize": 564487,
      "minHash": "19bc7a",
      "timestamp": 1691663614
    },
    "questPhases.2.json": {
      "key": "questPhases",
      "filename": "questPhases.2.json",
      "size": 1088924,
      "hash": "c84aa2",
      "minSize": 612987,
      "minHash": "e571b0",
      "timestamp": 1691663614
    },
    "questPhases.3.json": {
      "key": "questPhases",
      "filename": "questPhases.3.json",
      "size": 848326,
      "hash": "3cd18e",
      "minSize": 482725,
      "minHash": "c00f06",
      "timestamp": 1691667269
    },
    "extraMasterMission.json": {
      "key": "extraMasterMission",
      "filename": "extraMasterMission.json",
      "size": 1262196,
      "hash": "de8376",
      "minSize": 1016071,
      "minHash": "598700",
      "timestamp": 1690709824
    },
    "questGroups.json": {
      "key": "questGroups",
      "filename": "questGroups.json",
      "size": 976314,
      "hash": "0f7aa6",
      "minSize": 747792,
      "minHash": "3c4232",
      "timestamp": 1691313402
    },
    "constData.json": {
      "key": "constData",
      "filename": "constData.json",
      "size": 171098,
      "hash": "e796c8",
      "minSize": 120981,
      "minHash": "d18e21",
      "timestamp": 1690709824
    },
    "wiki.servants.1.json": {
      "key": "wiki.servants",
      "filename": "wiki.servants.1.json",
      "size": 195017,
      "hash": "a2e718",
      "minSize": 185937,
      "minHash": "03df2a",
      "timestamp": 1689604251
    },
    "wiki.servants.2.json": {
      "key": "wiki.servants",
      "filename": "wiki.servants.2.json",
      "size": 186748,
      "hash": "60c53b",
      "minSize": 178134,
      "minHash": "b34332",
      "timestamp": 1690716621
    },
    "wiki.servants.3.json": {
      "key": "wiki.servants",
      "filename": "wiki.servants.3.json",
      "size": 195633,
      "hash": "0020fb",
      "minSize": 187390,
      "minHash": "4a1645",
      "timestamp": 1691164201
    },
    "wiki.servants.4.json": {
      "key": "wiki.servants",
      "filename": "wiki.servants.4.json",
      "size": 617679,
      "hash": "3032ba",
      "minSize": 608555,
      "minHash": "648fca",
      "timestamp": 1691723153
    },
    "wiki.craftEssences.1.json": {
      "key": "wiki.craftEssences",
      "filename": "wiki.craftEssences.1.json",
      "size": 1041608,
      "hash": "6b9e35",
      "minSize": 1012925,
      "minHash": "d0f59e",
      "timestamp": 1690741915
    },
    "wiki.craftEssences.2.json": {
      "key": "wiki.craftEssences",
      "filename": "wiki.craftEssences.2.json",
      "size": 1105924,
      "hash": "7d423b",
      "minSize": 1076680,
      "minHash": "21655b",
      "timestamp": 1690925802
    },
    "wiki.craftEssences.3.json": {
      "key": "wiki.craftEssences",
      "filename": "wiki.craftEssences.3.json",
      "size": 1213464,
      "hash": "cb3abd",
      "minSize": 1183991,
      "minHash": "8387b2",
      "timestamp": 1691554882
    },
    "wiki.craftEssences.4.json": {
      "key": "wiki.craftEssences",
      "filename": "wiki.craftEssences.4.json",
      "size": 566711,
      "hash": "3baa3e",
      "minSize": 549110,
      "minHash": "690a06",
      "timestamp": 1691723153
    },
    "wiki.commandCodes.json": {
      "key": "wiki.commandCodes",
      "filename": "wiki.commandCodes.json",
      "size": 191617,
      "hash": "97ef3d",
      "minSize": 184608,
      "minHash": "6a9fe0",
      "timestamp": 1691671450
    },
    "wiki.events.json": {
      "key": "wiki.events",
      "filename": "wiki.events.json",
      "size": 354143,
      "hash": "7ae856",
      "minSize": 281437,
      "minHash": "d4bc91",
      "timestamp": 1691671450
    },
    "wiki.wars.json": {
      "key": "wiki.wars",
      "filename": "wiki.wars.json",
      "size": 17422,
      "hash": "baf614",
      "minSize": 15395,
      "minHash": "9a19b9",
      "timestamp": 1687272575
    },
    "wiki.summons.1.json": {
      "key": "wiki.summons",
      "filename": "wiki.summons.1.json",
      "size": 216949,
      "hash": "530b6c",
      "minSize": 158176,
      "minHash": "22c97b",
      "timestamp": 1680623037
    },
    "wiki.summons.2.json": {
      "key": "wiki.summons",
      "filename": "wiki.summons.2.json",
      "size": 802756,
      "hash": "934624",
      "minSize": 549952,
      "minHash": "0841c9",
      "timestamp": 1680623037
    },
    "wiki.summons.3.json": {
      "key": "wiki.summons",
      "filename": "wiki.summons.3.json",
      "size": 899067,
      "hash": "6e23e9",
      "minSize": 623506,
      "minHash": "5bf1af",
      "timestamp": 1682264376
    },
    "wiki.summons.4.json": {
      "key": "wiki.summons",
      "filename": "wiki.summons.4.json",
      "size": 748408,
      "hash": "1c91f8",
      "minSize": 525281,
      "minHash": "657e46",
      "timestamp": 1691723153
    },
    "wiki.summons.5.json": {
      "key": "wiki.summons",
      "filename": "wiki.summons.5.json",
      "size": 150907,
      "hash": "8ba7fd",
      "minSize": 107600,
      "minHash": "c2f0f6",
      "timestamp": 1691054148
    },
    "wiki.webcrowMapping.json": {
      "key": "wiki.webcrowMapping",
      "filename": "wiki.webcrowMapping.json",
      "size": 5023,
      "hash": "9a88d6",
      "minSize": 5023,
      "minHash": "9a88d6",
      "timestamp": 1685892733
    },
    "baseTds.json": {
      "key": "baseTds",
      "filename": "baseTds.json",
      "size": 1924006,
      "hash": "d99527",
      "minSize": 1264795,
      "minHash": "067217",
      "timestamp": 1691313402
    },
    "baseSkills.json": {
      "key": "baseSkills",
      "filename": "baseSkills.json",
      "size": 4175259,
      "hash": "fb64fd",
      "minSize": 3068685,
      "minHash": "fd717a",
      "timestamp": 1691667269
    },
    "baseFunctions.json": {
      "key": "baseFunctions",
      "filename": "baseFunctions.json",
      "size": 1127380,
      "hash": "6176e7",
      "minSize": 902534,
      "minHash": "a10c85",
      "timestamp": 1691313402
    }
  }
}
