{
  "timestamp": 1761901442,
  "utc": "2025-10-31T09:04:02",
  "minimalApp": "2.5.22",
  "files": {
    "items.json": {
      "key": "items",
      "filename": "items.json",
      "size": 969149,
      "hash": "909625",
      "minSize": 848916,
      "minHash": "3d806e",
      "timestamp": 1761555998
    },
    "entities.json": {
      "key": "entities",
      "filename": "entities.json",
      "size": 1833913,
      "hash": "3b301c",
      "minSize": 1385233,
      "minHash": "0f05e3",
      "timestamp": 1761555998
    },
    "bgms.json": {
      "key": "bgms",
      "filename": "bgms.json",
      "size": 548941,
      "hash": "06521e",
      "minSize": 452689,
      "minHash": "75ca46",
      "timestamp": 1761555998
    },
    "servants.1.json": {
      "key": "servants",
      "filename": "servants.1.json",
      "size": 1899933,
      "hash": "b667e5",
      "minSize": 1255185,
      "minHash": "1dd796",
      "timestamp": 1761131893
    },
    "servants.2.json": {
      "key": "servants",
      "filename": "servants.2.json",
      "size": 1814331,
      "hash": "3bac86",
      "minSize": 1196129,
      "minHash": "66ee3a",
      "timestamp": 1761131893
    },
    "servants.3.json": {
      "key": "servants",
      "filename": "servants.3.json",
      "size": 1902853,
      "hash": "0c5fb6",
      "minSize": 1253081,
      "minHash": "5d7b5b",
      "timestamp": 1761131893
    },
    "servants.4.json": {
      "key": "servants",
      "filename": "servants.4.json",
      "size": 1727651,
      "hash": "824f31",
      "minSize": 1142352,
      "minHash": "76fcd7",
      "timestamp": 1761296763
    },
    "servants.5.json": {
      "key": "servants",
      "filename": "servants.5.json",
      "size": 886434,
      "hash": "5563ef",
      "minSize": 571777,
      "minHash": "59fecf",
      "timestamp": 1761555998
    },
    "craftEssences.1.json": {
      "key": "craftEssences",
      "filename": "craftEssences.1.json",
      "size": 574426,
      "hash": "af8ace",
      "minSize": 411423,
      "minHash": "926b31",
      "timestamp": 1709727925
    },
    "craftEssences.2.json": {
      "key": "craftEssences",
      "filename": "craftEssences.2.json",
      "size": 598848,
      "hash": "6e795c",
      "minSize": 430876,
      "minHash": "e530e0",
      "timestamp": 1709727925
    },
    "craftEssences.3.json": {
      "key": "craftEssences",
      "filename": "craftEssences.3.json",
      "size": 608347,
      "hash": "d97d00",
      "minSize": 435823,
      "minHash": "3b9d89",
      "timestamp": 1743585600
    },
    "craftEssences.4.json": {
      "key": "craftEssences",
      "filename": "craftEssences.4.json",
      "size": 621147,
      "hash": "feacb9",
      "minSize": 445254,
      "minHash": "2de14b",
      "timestamp": 1717856996
    },
    "craftEssences.5.json": {
      "key": "craftEssences",
      "filename": "craftEssences.5.json",
      "size": 609390,
      "hash": "353764",
      "minSize": 440686,
      "minHash": "dbdc10",
      "timestamp": 1761555998
    },
    "craftEssences.6.json": {
      "key": "craftEssences",
      "filename": "craftEssences.6.json",
      "size": 12872,
      "hash": "423b9c",
      "minSize": 9212,
      "minHash": "0902e6",
      "timestamp": 1761555998
    },
    "commandCodes.json": {
      "key": "commandCodes",
      "filename": "commandCodes.json",
      "size": 174700,
      "hash": "7e2072",
      "minSize": 148836,
      "minHash": "a0ffc8",
      "timestamp": 1761131893
    },
    "mysticCodes.json": {
      "key": "mysticCodes",
      "filename": "mysticCodes.json",
      "size": 44266,
      "hash": "b00a5e",
      "minSize": 35891,
      "minHash": "47acd1",
      "timestamp": 1758809610
    },
    "exchangeTickets.json": {
      "key": "exchangeTickets",
      "filename": "exchangeTickets.json",
      "size": 11968,
      "hash": "8e98a5",
      "minSize": 9126,
      "minHash": "15355d",
      "timestamp": 1759244749
    },
    "enemyMasters.json": {
      "key": "enemyMasters",
      "filename": "enemyMasters.json",
      "size": 20010,
      "hash": "dfbcce",
      "minSize": 17476,
      "minHash": "9010d7",
      "timestamp": 1746024601
    },
    "classBoards.json": {
      "key": "classBoards",
      "filename": "classBoards.json",
      "size": 463526,
      "hash": "abeae6",
      "minSize": 299503,
      "minHash": "5e2205",
      "timestamp": 1760519193
    },
    "grandGraphs.json": {
      "key": "grandGraphs",
      "filename": "grandGraphs.json",
      "size": 12733,
      "hash": "f802c3",
      "minSize": 9910,
      "minHash": "15ac54",
      "timestamp": 1760519193
    },
    "masterMissions.json": {
      "key": "masterMissions",
      "filename": "masterMissions.json",
      "size": 79403,
      "hash": "dfc959",
      "minSize": 62860,
      "minHash": "04504d",
      "timestamp": 1761555998
    },
    "mappingData.1.json": {
      "key": "mappingData",
      "filename": "mappingData.1.json",
      "size": 3683294,
      "hash": "c4db02",
      "minSize": 3454897,
      "minHash": "ffc75c",
      "timestamp": 1742637213
    },
    "mappingData.2.json": {
      "key": "mappingData",
      "filename": "mappingData.2.json",
      "size": 1888319,
      "hash": "0ce5a0",
      "minSize": 1556039,
      "minHash": "05da63",
      "timestamp": 1742637213
    },
    "mappingData.3.json": {
      "key": "mappingData",
      "filename": "mappingData.3.json",
      "size": 3345841,
      "hash": "00d45d",
      "minSize": 2537979,
      "minHash": "6c0245",
      "timestamp": 1742637213
    },
    "mappingPatch.json": {
      "key": "mappingPatch",
      "filename": "mappingPatch.json",
      "size": 1580110,
      "hash": "708c4a",
      "minSize": 1374570,
      "minHash": "d4af44",
      "timestamp": 1761743416
    },
    "events.1.json": {
      "key": "events",
      "filename": "events.1.json",
      "size": 2791576,
      "hash": "e83f24",
      "minSize": 1946900,
      "minHash": "c94a8b",
      "timestamp": 1718184473
    },
    "events.2.json": {
      "key": "events",
      "filename": "events.2.json",
      "size": 3965358,
      "hash": "642b12",
      "minSize": 2867771,
      "minHash": "e6872e",
      "timestamp": 1720847859
    },
    "events.3.json": {
      "key": "events",
      "filename": "events.3.json",
      "size": 3815276,
      "hash": "9f9f2e",
      "minSize": 2719374,
      "minHash": "da8942",
      "timestamp": 1743585600
    },
    "events.4.json": {
      "key": "events",
      "filename": "events.4.json",
      "size": 5903354,
      "hash": "3294dd",
      "minSize": 4316875,
      "minHash": "582fab",
      "timestamp": 1761555998
    },
    "events.5.json": {
      "key": "events",
      "filename": "events.5.json",
      "size": 2244317,
      "hash": "f1838d",
      "minSize": 1581733,
      "minHash": "83756d",
      "timestamp": 1761555998
    },
    "wars.1.json": {
      "key": "wars",
      "filename": "wars.1.json",
      "size": 4190582,
      "hash": "c4cbde",
      "minSize": 2936362,
      "minHash": "ae9427",
      "timestamp": 1761555998
    },
    "wars.2.json": {
      "key": "wars",
      "filename": "wars.2.json",
      "size": 2643517,
      "hash": "b3a0e9",
      "minSize": 1797994,
      "minHash": "c9154c",
      "timestamp": 1761210396
    },
    "wars.3.json": {
      "key": "wars",
      "filename": "wars.3.json",
      "size": 2834307,
      "hash": "83c2f4",
      "minSize": 1952071,
      "minHash": "50c8bf",
      "timestamp": 1718184473
    },
    "wars.4.json": {
      "key": "wars",
      "filename": "wars.4.json",
      "size": 3835430,
      "hash": "f60da9",
      "minSize": 2679376,
      "minHash": "af0a60",
      "timestamp": 1718184473
    },
    "wars.5.json": {
      "key": "wars",
      "filename": "wars.5.json",
      "size": 4884922,
      "hash": "1fbfe5",
      "minSize": 3468672,
      "minHash": "4ce41e",
      "timestamp": 1761642360
    },
    "dropData.json": {
      "key": "dropData",
      "filename": "dropData.json",
      "size": 1315417,
      "hash": "f792d5",
      "minSize": 693951,
      "minHash": "6a50a8",
      "timestamp": 1761743416
    },
    "questPhases.1.json": {
      "key": "questPhases",
      "filename": "questPhases.1.json",
      "size": 1016638,
      "hash": "c47539",
      "minSize": 579876,
      "minHash": "09483a",
      "timestamp": 1760552939
    },
    "questPhases.2.json": {
      "key": "questPhases",
      "filename": "questPhases.2.json",
      "size": 1111375,
      "hash": "7d8427",
      "minSize": 627783,
      "minHash": "b09743",
      "timestamp": 1760552939
    },
    "questPhases.3.json": {
      "key": "questPhases",
      "filename": "questPhases.3.json",
      "size": 1107987,
      "hash": "02fe4f",
      "minSize": 632693,
      "minHash": "cacd24",
      "timestamp": 1760552939
    },
    "questPhases.4.json": {
      "key": "questPhases",
      "filename": "questPhases.4.json",
      "size": 303300,
      "hash": "1e8e4b",
      "minSize": 173291,
      "minHash": "bff7bc",
      "timestamp": 1760552939
    },
    "extraMasterMission.json": {
      "key": "extraMasterMission",
      "filename": "extraMasterMission.json",
      "size": 2490112,
      "hash": "151ab5",
      "minSize": 1985269,
      "minHash": "dde6c5",
      "timestamp": 1761555998
    },
    "questGroups.json": {
      "key": "questGroups",
      "filename": "questGroups.json",
      "size": 1095201,
      "hash": "8b6daf",
      "minSize": 839113,
      "minHash": "76b4d9",
      "timestamp": 1761642360
    },
    "questPhaseDetails.1.json": {
      "key": "questPhaseDetails",
      "filename": "questPhaseDetails.1.json",
      "size": 122120,
      "hash": "5994bb",
      "minSize": 92199,
      "minHash": "77ac77",
      "timestamp": 1733911505
    },
    "questPhaseDetails.2.json": {
      "key": "questPhaseDetails",
      "filename": "questPhaseDetails.2.json",
      "size": 470516,
      "hash": "f23f7f",
      "minSize": 354779,
      "minHash": "ce5cdf",
      "timestamp": 1743240019
    },
    "questPhaseDetails.3.json": {
      "key": "questPhaseDetails",
      "filename": "questPhaseDetails.3.json",
      "size": 755182,
      "hash": "724c82",
      "minSize": 569048,
      "minHash": "a33820",
      "timestamp": 1743240019
    },
    "questPhaseDetails.4.json": {
      "key": "questPhaseDetails",
      "filename": "questPhaseDetails.4.json",
      "size": 333639,
      "hash": "b498a4",
      "minSize": 252287,
      "minHash": "335ce9",
      "timestamp": 1761555998
    },
    "mstGacha.1.json": {
      "key": "mstGacha",
      "filename": "mstGacha.1.json",
      "size": 479880,
      "hash": "d02408",
      "minSize": 426469,
      "minHash": "256699",
      "timestamp": 1760886350
    },
    "mstGacha.2.json": {
      "key": "mstGacha",
      "filename": "mstGacha.2.json",
      "size": 387869,
      "hash": "555115",
      "minSize": 323692,
      "minHash": "a468fb",
      "timestamp": 1761642360
    },
    "campaigns.json": {
      "key": "campaigns",
      "filename": "campaigns.json",
      "size": 69061,
      "hash": "ee6a55",
      "minSize": 60855,
      "minHash": "bb0a45",
      "timestamp": 1761138752
    },
    "constData.json": {
      "key": "constData",
      "filename": "constData.json",
      "size": 245031,
      "hash": "511232",
      "minSize": 174026,
      "minHash": "c31276",
      "timestamp": 1760778768
    },
    "wiki.servants.1.json": {
      "key": "wiki.servants",
      "filename": "wiki.servants.1.json",
      "size": 142804,
      "hash": "cd148d",
      "minSize": 135691,
      "minHash": "100ea7",
      "timestamp": 1755267667
    },
    "wiki.servants.2.json": {
      "key": "wiki.servants",
      "filename": "wiki.servants.2.json",
      "size": 126853,
      "hash": "3491ea",
      "minSize": 120133,
      "minHash": "569ce5",
      "timestamp": 1759145901
    },
    "wiki.servants.3.json": {
      "key": "wiki.servants",
      "filename": "wiki.servants.3.json",
      "size": 131023,
      "hash": "0c6c5d",
      "minSize": 124161,
      "minHash": "c82a93",
      "timestamp": 1755173501
    },
    "wiki.servants.4.json": {
      "key": "wiki.servants",
      "filename": "wiki.servants.4.json",
      "size": 86129,
      "hash": "0f7fa5",
      "minSize": 81007,
      "minHash": "c933f2",
      "timestamp": 1756299934
    },
    "wiki.servants.5.json": {
      "key": "wiki.servants",
      "filename": "wiki.servants.5.json",
      "size": 196451,
      "hash": "98ecb9",
      "minSize": 192943,
      "minHash": "316a73",
      "timestamp": 1761743416
    },
    "wiki.craftEssences.1.json": {
      "key": "wiki.craftEssences",
      "filename": "wiki.craftEssences.1.json",
      "size": 1042087,
      "hash": "45fa1e",
      "minSize": 1013322,
      "minHash": "1d9028",
      "timestamp": 1760611528
    },
    "wiki.craftEssences.2.json": {
      "key": "wiki.craftEssences",
      "filename": "wiki.craftEssences.2.json",
      "size": 1107786,
      "hash": "7b05f0",
      "minSize": 1078281,
      "minHash": "5dec84",
      "timestamp": 1760611528
    },
    "wiki.craftEssences.3.json": {
      "key": "wiki.craftEssences",
      "filename": "wiki.craftEssences.3.json",
      "size": 1218928,
      "hash": "d22826",
      "minSize": 1189217,
      "minHash": "2a4a31",
      "timestamp": 1761743416
    },
    "wiki.craftEssences.4.json": {
      "key": "wiki.craftEssences",
      "filename": "wiki.craftEssences.4.json",
      "size": 1246406,
      "hash": "bea2b4",
      "minSize": 1217302,
      "minHash": "b5b744",
      "timestamp": 1761728774
    },
    "wiki.craftEssences.5.json": {
      "key": "wiki.craftEssences",
      "filename": "wiki.craftEssences.5.json",
      "size": 503183,
      "hash": "cd73af",
      "minSize": 483721,
      "minHash": "1d5073",
      "timestamp": 1761743416
    },
    "wiki.craftEssences.6.json": {
      "key": "wiki.craftEssences",
      "filename": "wiki.craftEssences.6.json",
      "size": 4107,
      "hash": "4996af",
      "minSize": 3831,
      "minHash": "0bea41",
      "timestamp": 1761555998
    },
    "wiki.commandCodes.json": {
      "key": "wiki.commandCodes",
      "filename": "wiki.commandCodes.json",
      "size": 297368,
      "hash": "15f24f",
      "minSize": 287240,
      "minHash": "69906d",
      "timestamp": 1761728774
    },
    "wiki.events.1.json": {
      "key": "wiki.events",
      "filename": "wiki.events.1.json",
      "size": 555459,
      "hash": "6b497c",
      "minSize": 438988,
      "minHash": "3e464e",
      "timestamp": 1761728774
    },
    "wiki.events.2.json": {
      "key": "wiki.events",
      "filename": "wiki.events.2.json",
      "size": 244102,
      "hash": "721d3b",
      "minSize": 212295,
      "minHash": "5c4bbf",
      "timestamp": 1761138752
    },
    "wiki.wars.json": {
      "key": "wiki.wars",
      "filename": "wiki.wars.json",
      "size": 22647,
      "hash": "dc9c73",
      "minSize": 19966,
      "minHash": "df2054",
      "timestamp": 1760552637
    },
    "wiki.summons.1.json": {
      "key": "wiki.summons",
      "filename": "wiki.summons.1.json",
      "size": 222762,
      "hash": "7ac671",
      "minSize": 163642,
      "minHash": "6818fa",
      "timestamp": 1735563501
    },
    "wiki.summons.2.json": {
      "key": "wiki.summons",
      "filename": "wiki.summons.2.json",
      "size": 809965,
      "hash": "c1426e",
      "minSize": 556644,
      "minHash": "c363f3",
      "timestamp": 1760360838
    },
    "wiki.summons.3.json": {
      "key": "wiki.summons",
      "filename": "wiki.summons.3.json",
      "size": 906246,
      "hash": "6263f9",
      "minSize": 630435,
      "minHash": "c8144e",
      "timestamp": 1735563501
    },
    "wiki.summons.4.json": {
      "key": "wiki.summons",
      "filename": "wiki.summons.4.json",
      "size": 766457,
      "hash": "df9132",
      "minSize": 541608,
      "minHash": "024c55",
      "timestamp": 1735407472
    },
    "wiki.summons.5.json": {
      "key": "wiki.summons",
      "filename": "wiki.summons.5.json",
      "size": 647408,
      "hash": "80a0a8",
      "minSize": 465424,
      "minHash": "f7f8cf",
      "timestamp": 1754053867
    },
    "wiki.summons.6.json": {
      "key": "wiki.summons",
      "filename": "wiki.summons.6.json",
      "size": 237819,
      "hash": "121e8e",
      "minSize": 179498,
      "minHash": "ecfcde",
      "timestamp": 1760533771
    },
    "wiki.summons.7.json": {
      "key": "wiki.summons",
      "filename": "wiki.summons.7.json",
      "size": 4673,
      "hash": "b834f3",
      "minSize": 4064,
      "minHash": "f9a884",
      "timestamp": 1761311501
    },
    "baseTds.json": {
      "key": "baseTds",
      "filename": "baseTds.json",
      "size": 2527226,
      "hash": "0901ec",
      "minSize": 1671781,
      "minHash": "1e1d7d",
      "timestamp": 1761555998
    },
    "baseSkills.json": {
      "key": "baseSkills",
      "filename": "baseSkills.json",
      "size": 6612460,
      "hash": "1ca476",
      "minSize": 4839265,
      "minHash": "e8c7f6",
      "timestamp": 1761555998
    },
    "baseFunctions.json": {
      "key": "baseFunctions",
      "filename": "baseFunctions.json",
      "size": 1801605,
      "hash": "30d067",
      "minSize": 1425502,
      "minHash": "36fc02",
      "timestamp": 1761555998
    },
    "addData.json": {
      "key": "addData",
      "filename": "addData.json",
      "size": 69,
      "hash": "a7fb3c",
      "minSize": 59,
      "minHash": "b6c711",
      "timestamp": 1761901442
    }
  }
}
