[
  {
    "id": 50000141,
    "imageId": 0,
    "name": "限时·序章冬木-呆毛",
    "type": 1,
    "openedAt": 1476349200,
    "closedAt": 1477807199
  },
  {
    "id": 50000131,
    "imageId": 0,
    "name": "300万DL-闪闪",
    "type": 1,
    "openedAt": 1476572400,
    "closedAt": 1477238399
  },
  {
    "id": 50000051,
    "imageId": 0,
    "name": "尼禄祭-阿蒂拉",
    "type": 1,
    "openedAt": 1477040400,
    "closedAt": 1477807199
  },
  {
    "id": 50000061,
    "imageId": 0,
    "name": "赏月少女-月神",
    "type": 1,
    "openedAt": 1477818000,
    "closedAt": 1478411999
  },
  {
    "id": 50000101,
    "imageId": 0,
    "name": "400万DL-金时",
    "type": 1,
    "openedAt": 1478422800,
    "closedAt": 1478879999
  },
  {
    "id": 50000071,
    "imageId": 0,
    "name": "万圣2016-玉藻前",
    "type": 1,
    "openedAt": 1479286800,
    "closedAt": 1480658399
  },
  {
    "id": 24211,
    "imageId": 0,
    "name": "剧情·三章俄刻阿诺斯-德雷克",
    "type": 1,
    "openedAt": 1480669200,
    "closedAt": 1481212799
  },
  {
    "id": 50000121,
    "imageId": 0,
    "name": "特选帅哥-诸葛孔明",
    "type": 1,
    "openedAt": 1481212800,
    "closedAt": 1481695199
  },
  {
    "id": 50000081,
    "imageId": 0,
    "name": "本能寺-冲田总司",
    "type": 1,
    "openedAt": 1481706000,
    "closedAt": 1483250399
  },
  {
    "id": 50000091,
    "imageId": 0,
    "name": "斯卡哈推荐-斯卡哈",
    "type": 1,
    "openedAt": 1483261200,
    "closedAt": 1483804799
  },
  {
    "id": 50000151,
    "imageId": 0,
    "name": "圣诞一期-杰克",
    "type": 1,
    "openedAt": 1483876800,
    "closedAt": 1484719199
  },
  {
    "id": 27211,
    "imageId": 0,
    "name": "剧情·四章伦敦-莫德雷德",
    "type": 1,
    "openedAt": 1484730000,
    "closedAt": 1485532799
  },
  {
    "id": 50000171,
    "imageId": 0,
    "name": "2017新年福袋",
    "type": 7,
    "openedAt": 1485532800,
    "closedAt": 1486137599
  },
  {
    "id": 50000161,
    "imageId": 0,
    "name": "2017新年日替-闪闪",
    "type": 1,
    "openedAt": 1485532800,
    "closedAt": 1485619199
  },
  {
    "id": 50000162,
    "imageId": 0,
    "name": "2017新年日替-迦尔纳",
    "type": 1,
    "openedAt": 1485619200,
    "closedAt": 1485705599
  },
  {
    "id": 50000163,
    "imageId": 0,
    "name": "2017新年日替-阿周那",
    "type": 1,
    "openedAt": 1485705600,
    "closedAt": 1485791999
  },
  {
    "id": 50000164,
    "imageId": 0,
    "name": "2017新年日替-坂田金时",
    "type": 1,
    "openedAt": 1485792000,
    "closedAt": 1485878399
  },
  {
    "id": 50000165,
    "imageId": 0,
    "name": "2017新年日替-斯卡哈",
    "type": 1,
    "openedAt": 1485878400,
    "closedAt": 1485964799
  },
  {
    "id": 50000166,
    "imageId": 0,
    "name": "2017新年日替-迦尔纳、阿周那",
    "type": 1,
    "openedAt": 1485964800,
    "closedAt": 1486051199
  },
  {
    "id": 50000167,
    "imageId": 0,
    "name": "2017新年日替-闪闪、迦尔纳、阿周那、坂田金时、斯卡哈",
    "type": 1,
    "openedAt": 1486051200,
    "closedAt": 1486137599
  },
  {
    "id": 29311,
    "imageId": 0,
    "name": "剧情·四章伦敦2-特斯拉",
    "type": 1,
    "openedAt": 1486137600,
    "closedAt": 1486792799
  },
  {
    "id": 50000181,
    "imageId": 0,
    "name": "SaberWars-X呆",
    "type": 1,
    "openedAt": 1486803600,
    "closedAt": 1488002399
  },
  {
    "id": 50000191,
    "imageId": 0,
    "name": "500万DL-布伦希尔德",
    "type": 1,
    "openedAt": 1488013200,
    "closedAt": 1488607199
  },
  {
    "id": 50000201,
    "imageId": 0,
    "name": "情人节-花嫁尼禄",
    "type": 1,
    "openedAt": 1488618000,
    "closedAt": 1488643199
  },
  {
    "id": 50000202,
    "imageId": 0,
    "name": "情人节-花嫁、呆毛",
    "type": 1,
    "openedAt": 1488643200,
    "closedAt": 1488729599
  },
  {
    "id": 50000203,
    "imageId": 0,
    "name": "情人节-花嫁、阿蒂拉",
    "type": 1,
    "openedAt": 1488729600,
    "closedAt": 1488815999
  },
  {
    "id": 50000204,
    "imageId": 0,
    "name": "情人节-花嫁、贞德",
    "type": 1,
    "openedAt": 1488816000,
    "closedAt": 1488902399
  },
  {
    "id": 50000205,
    "imageId": 0,
    "name": "情人节-花嫁、月神",
    "type": 1,
    "openedAt": 1488902400,
    "closedAt": 1488988799
  },
  {
    "id": 50000206,
    "imageId": 0,
    "name": "情人节-花嫁、玉藻前",
    "type": 1,
    "openedAt": 1488988800,
    "closedAt": 1489075199
  },
  {
    "id": 50000207,
    "imageId": 0,
    "name": "情人节-花嫁、德雷克",
    "type": 1,
    "openedAt": 1489075200,
    "closedAt": 1489161599
  },
  {
    "id": 50000208,
    "imageId": 0,
    "name": "情人节-花嫁、杰克",
    "type": 1,
    "openedAt": 1489161600,
    "closedAt": 1489247999
  },
  {
    "id": 50000209,
    "imageId": 0,
    "name": "情人节-花嫁、莫德雷德",
    "type": 1,
    "openedAt": 1489248000,
    "closedAt": 1489334399
  },
  {
    "id": 50000210,
    "imageId": 0,
    "name": "情人节-花嫁尼禄",
    "type": 1,
    "openedAt": 1489334400,
    "closedAt": 1489384799
  },
  {
    "id": 50000211,
    "imageId": 0,
    "name": "空境联动-两仪式",
    "type": 1,
    "openedAt": 1489395600,
    "closedAt": 1490680799
  },
  {
    "id": 50000221,
    "imageId": 0,
    "name": "白情-天草四郎",
    "type": 1,
    "openedAt": 1490691600,
    "closedAt": 1490716799
  },
  {
    "id": 50000222,
    "imageId": 0,
    "name": "白情-天草四郎",
    "type": 1,
    "openedAt": 1490716800,
    "closedAt": 1490803199
  },
  {
    "id": 50000223,
    "imageId": 0,
    "name": "白情-天草、大公",
    "type": 1,
    "openedAt": 1490803200,
    "closedAt": 1490889599
  },
  {
    "id": 50000224,
    "imageId": 0,
    "name": "白情-天草、孔明",
    "type": 1,
    "openedAt": 1490889600,
    "closedAt": 1490975999
  },
  {
    "id": 50000225,
    "imageId": 0,
    "name": "白情-天草、特斯拉",
    "type": 1,
    "openedAt": 1490976000,
    "closedAt": 1491062399
  },
  {
    "id": 50000226,
    "imageId": 0,
    "name": "白情-天草四郎",
    "type": 1,
    "openedAt": 1491062400,
    "closedAt": 1491371999
  },
  {
    "id": 50000231,
    "imageId": 0,
    "name": "监狱塔-岩窟王",
    "type": 1,
    "openedAt": 1491382800,
    "closedAt": 1492063199
  },
  {
    "id": 50000241,
    "imageId": 0,
    "name": "迦尔纳、阿周那-迦尔纳、阿周那",
    "type": 1,
    "openedAt": 1492074000,
    "closedAt": 1492099199
  },
  {
    "id": 50000242,
    "imageId": 0,
    "name": "迦尔纳-迦尔纳",
    "type": 1,
    "openedAt": 1492099200,
    "closedAt": 1492185599
  },
  {
    "id": 50000243,
    "imageId": 0,
    "name": "阿周那-阿周那",
    "type": 1,
    "openedAt": 1492185600,
    "closedAt": 1492271999
  },
  {
    "id": 50000244,
    "imageId": 0,
    "name": "迦尔纳-迦尔纳",
    "type": 1,
    "openedAt": 1492272000,
    "closedAt": 1492358399
  },
  {
    "id": 50000245,
    "imageId": 0,
    "name": "阿周那-阿周那",
    "type": 1,
    "openedAt": 1492358400,
    "closedAt": 1492444799
  },
  {
    "id": 50000246,
    "imageId": 0,
    "name": "迦尔纳-迦尔纳",
    "type": 1,
    "openedAt": 1492444800,
    "closedAt": 1492531199
  },
  {
    "id": 50000247,
    "imageId": 0,
    "name": "阿周那-阿周那",
    "type": 1,
    "openedAt": 1492531200,
    "closedAt": 1492617599
  },
  {
    "id": 50000248,
    "imageId": 0,
    "name": "迦尔纳、阿周那-迦尔纳、阿周那",
    "type": 1,
    "openedAt": 1492617600,
    "closedAt": 1492667999
  },
  {
    "id": 35506,
    "imageId": 0,
    "name": "剧情·五章美利坚1-南丁",
    "type": 1,
    "openedAt": 1493197200,
    "closedAt": 1493737199
  },
  {
    "id": 50000251,
    "imageId": 0,
    "name": "赝作-黑贞",
    "type": 1,
    "openedAt": 1493802000,
    "closedAt": 1494655199
  },
  {
    "id": 5000261,
    "imageId": 0,
    "name": "FZ预热-闪闪、呆毛",
    "type": 1,
    "openedAt": 1494666000,
    "closedAt": 1494691199
  },
  {
    "id": 5000262,
    "imageId": 0,
    "name": "FZ预热-闪闪",
    "type": 1,
    "openedAt": 1494691200,
    "closedAt": 1494777599
  },
  {
    "id": 5000263,
    "imageId": 0,
    "name": "FZ预热-呆毛",
    "type": 1,
    "openedAt": 1494777600,
    "closedAt": 1494863999
  },
  {
    "id": 5000264,
    "imageId": 0,
    "name": "FZ预热-闪闪",
    "type": 1,
    "openedAt": 1494864000,
    "closedAt": 1494950399
  },
  {
    "id": 5000265,
    "imageId": 0,
    "name": "FZ预热-呆毛",
    "type": 1,
    "openedAt": 1494950400,
    "closedAt": 1495036799
  },
  {
    "id": 5000266,
    "imageId": 0,
    "name": "FZ预热-闪闪",
    "type": 1,
    "openedAt": 1495036800,
    "closedAt": 1495123199
  },
  {
    "id": 5000267,
    "imageId": 0,
    "name": "FZ预热-闪闪、呆毛",
    "type": 1,
    "openedAt": 1495123200,
    "closedAt": 1495173599
  },
  {
    "id": 5000271,
    "imageId": 0,
    "name": "FZ联动-大帝",
    "type": 1,
    "openedAt": 1495184400,
    "closedAt": 1495727999
  },
  {
    "id": 5000272,
    "imageId": 0,
    "name": "FZ联动-大帝、孔明",
    "type": 1,
    "openedAt": 1495728000,
    "closedAt": 1495814399
  },
  {
    "id": 5000273,
    "imageId": 0,
    "name": "FZ联动-大帝",
    "type": 1,
    "openedAt": 1495814400,
    "closedAt": 1495900799
  },
  {
    "id": 5000274,
    "imageId": 0,
    "name": "FZ联动-大帝、孔明",
    "type": 1,
    "openedAt": 1495900800,
    "closedAt": 1495987199
  },
  {
    "id": 5000275,
    "imageId": 0,
    "name": "FZ联动-大帝",
    "type": 1,
    "openedAt": 1495987200,
    "closedAt": 1496073599
  },
  {
    "id": 5000276,
    "imageId": 0,
    "name": "FZ联动-大帝、孔明",
    "type": 1,
    "openedAt": 1496073600,
    "closedAt": 1496159999
  },
  {
    "id": 5000277,
    "imageId": 0,
    "name": "FZ联动-大帝",
    "type": 1,
    "openedAt": 1496160000,
    "closedAt": 1496246399
  },
  {
    "id": 5000278,
    "imageId": 0,
    "name": "FZ联动-大帝、孔明",
    "type": 1,
    "openedAt": 1496246400,
    "closedAt": 1496332799
  },
  {
    "id": 5000279,
    "imageId": 0,
    "name": "FZ联动-大帝",
    "type": 1,
    "openedAt": 1496332800,
    "closedAt": 1496987999
  },
  {
    "id": 3900100,
    "imageId": 0,
    "name": "限时·五章美利坚2-梅芙",
    "type": 1,
    "openedAt": 1497085200,
    "closedAt": 1497592799
  },
  {
    "id": 4100100,
    "imageId": 0,
    "name": "限时·五章美利坚3-黑狗",
    "type": 1,
    "openedAt": 1497603600,
    "closedAt": 1498233599
  },
  {
    "id": 5000281,
    "imageId": 0,
    "name": "坂田金时推荐-坂田金时",
    "type": 1,
    "openedAt": 1498233600,
    "closedAt": 1498802399
  },
  {
    "id": 5000291,
    "imageId": 0,
    "name": "罗生门-酒吞童子",
    "type": 1,
    "openedAt": 1498813200,
    "closedAt": 1500098399
  },
  {
    "id": 5000301,
    "imageId": 0,
    "name": "西游-三藏",
    "type": 1,
    "openedAt": 1500109200,
    "closedAt": 1501307999
  },
  {
    "id": 5000311,
    "imageId": 0,
    "name": "600万DL-斯卡哈",
    "type": 1,
    "openedAt": 1501318800,
    "closedAt": 1502171999
  },
  {
    "id": 5000321,
    "imageId": 0,
    "name": "鬼岛-源赖光",
    "type": 1,
    "openedAt": 1502182800,
    "closedAt": 1503413999
  },
  {
    "id": 450007,
    "imageId": 0,
    "name": "剧情·六章卡美洛-拉二",
    "type": 1,
    "openedAt": 1504256400,
    "closedAt": 1505023199
  },
  {
    "id": 4700001,
    "imageId": 0,
    "name": "限时·六章卡美洛2-白枪呆",
    "type": 1,
    "openedAt": 1505034000,
    "closedAt": 1505973599
  },
  {
    "id": 5000341,
    "imageId": 0,
    "name": "一周年福袋",
    "type": 7,
    "openedAt": 1505984400,
    "closedAt": 1506751199
  },
  {
    "id": 5000351,
    "imageId": 0,
    "name": "一周年卡池-达芬奇",
    "type": 1,
    "openedAt": 1505984400,
    "closedAt": 1506182399
  },
  {
    "id": 5000352,
    "imageId": 0,
    "name": "一周年+序章-达芬奇、呆毛",
    "type": 1,
    "openedAt": 1506182400,
    "closedAt": 1506268799
  },
  {
    "id": 5000353,
    "imageId": 0,
    "name": "一周年+一章-达芬奇、贞德",
    "type": 1,
    "openedAt": 1506268800,
    "closedAt": 1506355199
  },
  {
    "id": 5000354,
    "imageId": 0,
    "name": "一周年+二章-达芬奇、阿蒂拉",
    "type": 1,
    "openedAt": 1506355200,
    "closedAt": 1506441599
  },
  {
    "id": 5000355,
    "imageId": 0,
    "name": "一周年+三章-达芬奇、德雷克",
    "type": 1,
    "openedAt": 1506441600,
    "closedAt": 1506527999
  },
  {
    "id": 5000356,
    "imageId": 0,
    "name": "一周年+四章-达芬奇、莫德雷德、特斯拉",
    "type": 1,
    "openedAt": 1506528000,
    "closedAt": 1506614399
  },
  {
    "id": 5000357,
    "imageId": 0,
    "name": "一周年+五章-达芬奇、南丁、梅芙、黑狗",
    "type": 1,
    "openedAt": 1506614400,
    "closedAt": 1506751199
  },
  {
    "id": 5000361,
    "imageId": 0,
    "name": "泳装一期-水玉藻",
    "type": 1,
    "openedAt": 1506762000,
    "closedAt": 1508479199
  },
  {
    "id": 5000362,
    "imageId": 0,
    "name": "泳装一期2-弓呆",
    "type": 1,
    "openedAt": 1507366800,
    "closedAt": 1508479199
  },
  {
    "id": 5000371,
    "imageId": 0,
    "name": "魔伊联动-伊莉雅",
    "type": 1,
    "openedAt": 1508490000,
    "closedAt": 1509033599
  },
  {
    "id": 5000372,
    "imageId": 0,
    "name": "魔伊联动-梅芙",
    "type": 1,
    "openedAt": 1509033600,
    "closedAt": 1509119999
  },
  {
    "id": 5000373,
    "imageId": 0,
    "name": "魔伊联动-伊莉雅、梅芙",
    "type": 1,
    "openedAt": 1509120000,
    "closedAt": 1509206399
  },
  {
    "id": 5000374,
    "imageId": 0,
    "name": "魔伊联动-梅芙",
    "type": 1,
    "openedAt": 1509206400,
    "closedAt": 1509292799
  },
  {
    "id": 5000375,
    "imageId": 0,
    "name": "魔伊联动-伊莉雅",
    "type": 1,
    "openedAt": 1509292800,
    "closedAt": 1509688799
  },
  {
    "id": 5000381,
    "imageId": 0,
    "name": "职介区别1 Saber-阿尔托莉雅、阿蒂拉、莫德雷德",
    "type": 1,
    "openedAt": 1509699600,
    "closedAt": 1509724799
  },
  {
    "id": 5000382,
    "imageId": 0,
    "name": "职介区别1 Archer-月神、特斯拉、阿周那",
    "type": 1,
    "openedAt": 1509724800,
    "closedAt": 1509811199
  },
  {
    "id": 5000383,
    "imageId": 0,
    "name": "职介区别1 Lancer-迦尔纳、白枪呆",
    "type": 1,
    "openedAt": 1509811200,
    "closedAt": 1509897599
  },
  {
    "id": 5000384,
    "imageId": 0,
    "name": "职介区别1 Rider-德雷克、梅芙、拉二",
    "type": 1,
    "openedAt": 1509897600,
    "closedAt": 1509983999
  },
  {
    "id": 5000385,
    "imageId": 0,
    "name": "职介区别1 Assassin+Ex-杰克、贞德",
    "type": 1,
    "openedAt": 1509984000,
    "closedAt": 1510070399
  },
  {
    "id": 5000386,
    "imageId": 0,
    "name": "职介区别1 Caster-诸葛孔明、玉藻前、三藏",
    "type": 1,
    "openedAt": 1510070400,
    "closedAt": 1510156799
  },
  {
    "id": 5000387,
    "imageId": 0,
    "name": "职介区别1 Berserker-大公、南丁、黑狗",
    "type": 1,
    "openedAt": 1510156800,
    "closedAt": 1510243199
  },
  {
    "id": 5000388,
    "imageId": 0,
    "name": "职介区别1 Saber-阿尔托莉雅、阿蒂拉、莫德雷德",
    "type": 1,
    "openedAt": 1510243200,
    "closedAt": 1510293599
  },
  {
    "id": 5000390,
    "imageId": 0,
    "name": "尼禄祭再临-花嫁尼禄",
    "type": 1,
    "openedAt": 1510304400,
    "closedAt": 1511503199
  },
  {
    "id": 5000400,
    "imageId": 0,
    "name": "700万DL-黑贞",
    "type": 1,
    "openedAt": 1510909200,
    "closedAt": 1511503199
  },
  {
    "id": 5000410,
    "imageId": 0,
    "name": "万圣1复刻-玉藻前",
    "type": 1,
    "openedAt": 1511521200,
    "closedAt": 1512712799
  },
  {
    "id": 5000420,
    "imageId": 0,
    "name": "万圣2-艳后",
    "type": 1,
    "openedAt": 1512122400,
    "closedAt": 1513317599
  },
  {
    "id": 5000430,
    "imageId": 0,
    "name": "F/E发售纪念-呆毛、阿蒂拉、迦尔纳、德雷克、玉藻前、贞德",
    "type": 1,
    "openedAt": 1513328400,
    "closedAt": 1513835999
  },
  {
    "id": 5000440,
    "imageId": 0,
    "name": "圆桌骑士-呆毛、莫德雷德、白枪呆",
    "type": 1,
    "openedAt": 1513846800,
    "closedAt": 1514440799
  },
  {
    "id": 5000450,
    "imageId": 0,
    "name": "圣诞1复刻-杰克",
    "type": 1,
    "openedAt": 1513846800,
    "closedAt": 1514872799
  },
  {
    "id": 5000460,
    "imageId": 0,
    "name": "圣诞二期-弓凛",
    "type": 1,
    "openedAt": 1514883600,
    "closedAt": 1515855599
  },
  {
    "id": 5000470,
    "imageId": 0,
    "name": "阿蒂拉推荐-阿蒂拉",
    "type": 1,
    "openedAt": 1514883600,
    "closedAt": 1515855599
  },
  {
    "id": 5000480,
    "imageId": 0,
    "name": "天草四郎推荐-天草四郎",
    "type": 1,
    "openedAt": 1514883600,
    "closedAt": 1515855599
  },
  {
    "id": 500008,
    "imageId": 0,
    "name": "剧情·七章巴比伦-恩奇都",
    "type": 1,
    "openedAt": 1515920400,
    "closedAt": 1517896799
  },
  {
    "id": 5000490,
    "imageId": 0,
    "name": "限时·七章巴比伦2-羽蛇神",
    "type": 1,
    "openedAt": 1516464000,
    "closedAt": 1517896799
  },
  {
    "id": 5000500,
    "imageId": 0,
    "name": "终章所罗门-梅林",
    "type": 1,
    "openedAt": 1516705200,
    "closedAt": 1517896799
  },
  {
    "id": 5000570,
    "imageId": 0,
    "name": "800万DL-达芬奇",
    "type": 1,
    "openedAt": 1521018000,
    "closedAt": 1521903599
  },
  {
    "id": 5000877,
    "imageId": 0,
    "name": "2019新年福袋-下四",
    "type": 7,
    "openedAt": 1549296000,
    "closedAt": 1550901599
  }
]
